dktotoolkit/__init__.py
dktotoolkit/__version__.py
dktotoolkit/datestr.py
dktotoolkit/dict.py
dktotoolkit/exceptions.py
dktotoolkit/function_recursive.py
dktotoolkit/functions.py
dktotoolkit/html.py
dktotoolkit/jsonlike.py
dktotoolkit/list.py
dktotoolkit/sqlite3.py
dktotoolkit/aelf/__init__.py
dktotoolkit/aelf/_call_api.py
dktotoolkit/aelf/_get_office.py
dktotoolkit/aelf/_office_content_to_elements.py
dktotoolkit/discordify/__init__.py
dktotoolkit/discordify/main.py
dktotoolkit/envvar/__init__.py
dktotoolkit/envvar/_load_dotenv.py
dktotoolkit/envvar/_task_watch_dotenv.py
dktotoolkit/parserhtml/__init__.py
dktotoolkit/parserhtml/_clean_html.py
dktotoolkit/parserhtml/_decode_html_special_chars.py
dktotoolkit/parserhtml/_html_2_markdown.py
dktotoolkit/parserhtml/_keep_only_selected_tags.py
dktotoolkit/parserhtml/_remove_duplicate_tags.py
dktotoolkit/parserhtml/_replace_span_with_bold_and_italic.py
dktotoolkit/parserhtml/html_mapping.py
dktotoolkit/parserhtml/markdown_2_html.py
dktotoolkit/str/__init__.py
dktotoolkit/str/_splitContent.py
dktotoolkit/str/_str_to_digit.py
dktotoolkit/verbose/__init__.py
dktotoolkit-1.1.0.dist-info/LICENSE
dktotoolkit-1.1.0.dist-info/METADATA
dktotoolkit-1.1.0.dist-info/WHEEL
dktotoolkit-1.1.0.dist-info/top_level.txt
dktotoolkit-1.1.0.dist-info/RECORD
