Metadata-Version: 2.1
Name: dktotoolkit
Version: 1.1.0
Summary: A little toolkit with fancy functions
Home-page: https://discord-catho.frama.io/module_toolkit
Author: Pierre
Author-email: pierre@exemple.com
License: AGPL 3
Keywords: dotenv,.env,toolkit,parse dates
Classifier: Development Status :: 3 - Alpha
Classifier: Intended Audience :: Developers
Classifier: Programming Language :: Python :: 3.9
Classifier: Environment :: Console
Classifier: Operating System :: POSIX :: Linux
Classifier: Natural Language :: French
Classifier: Natural Language :: English
Classifier: License :: OSI Approved :: GNU Affero General Public License v3
Classifier: Operating System :: OS Independent
Requires-Python: >=3.9, <4
License-File: LICENSE
Requires-Dist: bs4 ==0.0.1
Requires-Dist: markdownify ==0.11.6
Requires-Dist: requests ==2.28.2
Provides-Extra: doc
Requires-Dist: sphinx >=7.2.6 ; extra == 'doc'
Requires-Dist: sphinx-rtd-theme >=1.3.0 ; extra == 'doc'
Requires-Dist: myst-parser >=2.0.0 ; extra == 'doc'
Provides-Extra: test
Requires-Dist: coverage >=7.3.1 ; extra == 'test'
Requires-Dist: flake8 >=6.1.0 ; extra == 'test'
Requires-Dist: flake8-html >=0.4.3 ; extra == 'test'
Requires-Dist: html-report-line-profiler >=0.1.1a ; extra == 'test'
Provides-Extra: upload
Requires-Dist: twine >=4.0.2 ; extra == 'upload'
Requires-Dist: wheel >=0.40.0 ; extra == 'upload'
